omero_web_zarr/__init__.py
omero_web_zarr/apps.py
omero_web_zarr/urls.py
omero_web_zarr/utils.py
omero_web_zarr/views.py
omero_web_zarr/static/omero_web_zarr/openwith.js
omero_web_zarr/static/omero_web_zarr/openwith_validator.js
omero_web_zarr-0.1.1.dist-info/LICENSE
omero_web_zarr-0.1.1.dist-info/METADATA
omero_web_zarr-0.1.1.dist-info/WHEEL
omero_web_zarr-0.1.1.dist-info/top_level.txt
omero_web_zarr-0.1.1.dist-info/RECORD
